infinityvoid/__init__.py
infinityvoid/ALL_PRACT_EASY/Information_Security.pkt
infinityvoid/ALL_PRACT_EASY/aaa.pkt
infinityvoid/ALL_PRACT_EASY/acl.pkt
infinityvoid/ALL_PRACT_EASY/asa_fire[1].pkt
infinityvoid/ALL_PRACT_EASY/firewall[1].pkt
infinityvoid/ALL_PRACT_EASY/ips[1].pkt
infinityvoid/ALL_PRACT_EASY/layer2[1].pkt
"infinityvoid/ALL_PRACT_EASY/syslog,ntp,ssh.pkt"
infinityvoid/ALL_PRACT_EASY/vlan[1].pkt
infinityvoid/ALL_PRACT_PROPER/IOS IPS.docx
infinityvoid/ALL_PRACT_PROPER/PRACTICAL NO 1.docx
infinityvoid/ALL_PRACT_PROPER/PRACTICAL NO AAA.docx
infinityvoid/ALL_PRACT_PROPER/PRACTICAL NO ACL.docx
infinityvoid/ALL_PRACT_PROPER/PRACTICAL VPN Tunnel.docx
infinityvoid/ALL_PRACT_PROPER/Practical No ipv6 .docx
infinityvoid/ALL_PRACT_PROPER/Zonebased firewall.docx
infinityvoid/ALL_PRACT_PROPER/layer 2 security neww.docx
infinityvoid/ALL_PRACT_PROPER/mr10[1][1].docx
infinityvoid/ALL_PRACT_PROPER/vlanSecurityFinal.docx
infinityvoid-0.6.dist-info/METADATA
infinityvoid-0.6.dist-info/WHEEL
infinityvoid-0.6.dist-info/top_level.txt
infinityvoid-0.6.dist-info/RECORD
