Metadata-Version: 2.1
Name: infinityvoid
Version: 0.6
Summary: A module with a PDF and Python file
Home-page: https://example.com/mymodule
Author: Your Name
Author-email: your.email@example.com
